Metadata-Version: 2.1
Name: show-image-mat2
Version: 0.0.1
Summary: Um repositório não oficial para exibir imagens
Home-page: UNKNOWN
Author: Marcelo Torres
Author-email: marcelotores21@gmail.com
License: MIT License
Keywords: matplotlib
Platform: UNKNOWN
License-File: LICENCE
